{
  "name": "entity.minecells.mutated_bat",
  "category": "minecells:mobs",
  "icon": "minecells:mutated_bat_spawn_egg",
  "advancement": "minecells:book/mobs/mutated_bat",
  "pages": [
    {
      "type": "minecells:entity",
      "entity": "minecells:mutated_bat",
      "title": "entity.minecells.mutated_bat",
      "text": "book.minecells.entries.mobs.mutated_bat"
    },
    {
      "type": "minecells:references",
      "content": [
        "# book.minecells.common.found_in",
        "minecells:dimensions/promenade"
      ]
    }
  ]
}